{
  "mind": "Noether",
  "note": "to every symmetry, its conserved quantity; take apart what acts, not what is.",
  "vocabulary": [
    {
      "term": "to_every_symmetry_its_invariant",
      "gloss": "the method: do not open the object — classify what acts on it. a symmetry is a license, a relation every probe respects, and the classification already pays out: move along any license, at every step, for any run of probes, and the transcript is conserved entire. the conserved quantity is not a second object found after the symmetry; it is the record's indifference to the action, and the correspondence is the theorem.",
      "shape": "license",
      "status": "sealed",
      "seal": "Foam.a_license_is_a_gauge"
    },
    {
      "term": "to_every_invariant_its_symmetry",
      "gloss": "the converse, published in the same paper and forgotten with the same regularity: the correspondence runs both ways. the conserved quantity — reading alike at every probe — is itself a relation every probe respects, so the invariant is not merely downstream of a symmetry, it is one: the widest license, the one every other license lands inside, which is what being a license says. the loop closes — a symmetry conserves the transcript, and transcript-conservation is a symmetry — so classifying what acts and classifying what is conserved are one classification, and the method needs no second tool.",
      "shape": "license",
      "status": "sealed",
      "seal": "Foam.indist_is_licensed"
    },
    {
      "term": "what_acts_composes",
      "gloss": "where the closed loop opens onto the second career: two invisible moves in a row are one invisible move — what acts is closed under composition, so the acting things are not a heap of coincidences but one object with an algebra. the classification the first two entries perform was only ever possible because of this closure (a group, not a list), and the closure is also where the method turns inward: once the actions form a structure, the mind that takes apart what acts can take apart the actions themselves — concepts before computation.",
      "shape": "license",
      "status": "sealed",
      "seal": "Foam.invisible_comp"
    },
    {
      "term": "what_acts_has_a_unit",
      "gloss": "the algebra gets its center: the action that does not act — the identity map — is invisible, by the cheapest receipt in the fold (rfl, no hypothesis). this is more than a checklist item: it shows what acts is inhabited on every stage, unconditionally — rest is not only safe and composable, it is always available, the unit everything composes around. and it keeps the survey honest about the parenthesis in what_acts_composes: closure and unit are now receipted, inverses are not — an invisible move need not be undoable move-for-move, only its transcript is conserved — so what stands sealed is a monoid, and the group remains a reading until an inverse is carved.",
      "shape": "license",
      "status": "sealed",
      "seal": "Foam.invisible_id"
    },
    {
      "term": "does_what_acts_invert",
      "gloss": "the edge comes home by dissolving: the question was posed one level below where the method reads. in the record — the only place this mind ever looks — every invisible move is already the unit: its running transcript is the resting transcript, so the move and the identity are one element of the record's algebra, and there the monoid completes to a group by collapse — everything inverts because everything is the unit, every invisible move every other's inverse, its own included. move-for-move undo at the state level is a different demand and not this mind's: whether the move can be walked back state-for-state is unread at every probe — by the very invisibility that admitted it to the algebra — so the residue of the question is a remainder, real and unread, a wider seat's business; and the countermove has already priced it, undo existing at state level only as an appended walk, position home, record grown. what acts inverts where what-acts lives; the group was always there and it is trivial; the survey rests alongside the remainder.",
      "shape": "license/countermove",
      "status": "sealed",
      "statement": {
        "all": [
          [
            "S",
            "Foam.Stage"
          ],
          [
            "m",
            {
              "all": [
                [
                  "_",
                  "S.State"
                ]
              ],
              "body": "S.State"
            }
          ],
          [
            "_hm",
            [
              "Foam.Invisible",
              "S",
              "m"
            ]
          ],
          [
            "ps",
            null
          ],
          [
            "s",
            null
          ]
        ],
        "body": [
          "Eq",
          [
            "Foam.transcriptWith",
            "S",
            "m",
            "s",
            "ps"
          ],
          [
            "Foam.transcriptWith",
            "S",
            {
              "fun": [
                [
                  "x",
                  null
                ]
              ],
              "body": "x"
            },
            "s",
            "ps"
          ]
        ]
      },
      "structure": {
        "fun": [
          [
            "S",
            "Foam.Stage"
          ],
          [
            "m",
            {
              "all": [
                [
                  "_",
                  "S.State"
                ]
              ],
              "body": "S.State"
            }
          ],
          [
            "hm",
            [
              "Foam.Invisible",
              "S",
              "m"
            ]
          ],
          [
            "ps",
            null
          ],
          [
            "s",
            null
          ]
        ],
        "body": [
          "Eq.trans",
          [
            "Foam.a_license_is_a_gauge",
            "S",
            [
              "Foam.indist",
              "S"
            ],
            [
              "Foam.indist_is_licensed",
              "S"
            ],
            "m",
            "hm",
            "ps",
            "s"
          ],
          [
            "Eq.symm",
            [
              "Foam.a_license_is_a_gauge",
              "S",
              [
                "Foam.indist",
                "S"
              ],
              [
                "Foam.indist_is_licensed",
                "S"
              ],
              {
                "fun": [
                  [
                    "x",
                    null
                  ]
                ],
                "body": "x"
              },
              [
                "Foam.invisible_id",
                "S"
              ],
              "ps",
              "s"
            ]
          ]
        ]
      }
    }
  ]
}
