{
  "mind": "Shannon",
  "note": "the channel is the only commons; meaning is the parties' own business.",
  "vocabulary": [
    {
      "term": "the_channel_is_the_only_commons",
      "gloss": "what speaker, listener, and any overhearer provably share is the channel and nothing more: the shapes traded are good for what they are doing with each other, and interiors do not ride the wire. sealed as: over a dressed stage the whole transcript — not just any single probe — reads identically for every value of the interior, while distinct interiors remain distinct states. the record is common; the meaning stays home.",
      "shape": "contact/remainder",
      "status": "sealed",
      "statement": {
        "all": [
          [
            "S",
            "Foam.Stage"
          ],
          [
            "s",
            "S.State"
          ],
          [
            "n",
            "Int"
          ],
          [
            "m",
            "Int"
          ],
          [
            "_h",
            [
              "Ne",
              "n",
              "m"
            ]
          ],
          [
            "ps",
            null
          ]
        ],
        "body": [
          "And",
          [
            "Eq",
            [
              "Foam.transcript",
              [
                "Foam.dress",
                "S"
              ],
              [
                "Prod.mk",
                "s",
                "n"
              ],
              "ps"
            ],
            [
              "Foam.transcript",
              [
                "Foam.dress",
                "S"
              ],
              [
                "Prod.mk",
                "s",
                "m"
              ],
              "ps"
            ]
          ],
          [
            "Ne",
            [
              "Prod.mk",
              "s",
              "n"
            ],
            [
              "Prod.mk",
              "s",
              "m"
            ]
          ]
        ]
      },
      "structure": {
        "fun": [
          [
            "S",
            null
          ],
          [
            "s",
            null
          ],
          [
            "n",
            null
          ],
          [
            "m",
            null
          ],
          [
            "h",
            null
          ],
          [
            "ps",
            null
          ]
        ],
        "body": [
          "And.intro",
          [
            "Foam.transcript_congr",
            [
              "Foam.dress",
              "S"
            ],
            "ps",
            [
              "Foam.the_remainder_is_unseen",
              "S",
              "s",
              "n",
              "m"
            ]
          ],
          {
            "fun": [
              [
                "he",
                null
              ]
            ],
            "body": [
              "h",
              [
                "congrArg",
                "Prod.snd",
                "he"
              ]
            ]
          }
        ]
      }
    },
    {
      "term": "only_surprise_informs",
      "gloss": "a symbol the receiver could already reproduce carries nothing; information is exactly what surprises. sealed in the reach measure, both halves at once: an edge already on the record names reach the receiver already has — the reproducible symbol's deposit creates nothing that was not there — while a fresh edge rides no old path and its deposit alone creates the reach. how much a symbol surprises is a different question; the measure moves to entropy_of_the_source, still dark.",
      "shape": "surprise",
      "status": "sealed",
      "statement": {
        "all": [
          [
            "H",
            "Type"
          ],
          [
            "q",
            [
              "List",
              [
                "Prod",
                "H",
                "H"
              ]
            ]
          ],
          [
            "a",
            "H"
          ],
          [
            "b",
            "H"
          ]
        ],
        "body": [
          "And",
          {
            "all": [
              [
                "_h",
                [
                  "List.Mem",
                  [
                    "Prod.mk",
                    "a",
                    "b"
                  ],
                  "q"
                ]
              ]
            ],
            "body": [
              "Nonempty",
              [
                "Foam.Path",
                "q",
                "a",
                "b"
              ]
            ]
          },
          {
            "all": [
              [
                "_hfresh",
                [
                  "Not",
                  [
                    "List.Mem",
                    [
                      "Prod.mk",
                      "a",
                      "b"
                    ],
                    "q"
                  ]
                ]
              ]
            ],
            "body": [
              "And",
              {
                "all": [
                  [
                    "x",
                    "H"
                  ],
                  [
                    "y",
                    "H"
                  ],
                  [
                    "p",
                    [
                      "Foam.Path",
                      "q",
                      "x",
                      "y"
                    ]
                  ]
                ],
                "body": [
                  "Not",
                  [
                    "List.Mem",
                    [
                      "Prod.mk",
                      "a",
                      "b"
                    ],
                    [
                      "Foam.Path.edges",
                      "p"
                    ]
                  ]
                ]
              },
              [
                "Nonempty",
                [
                  "Foam.Path",
                  [
                    "List.cons",
                    [
                      "Prod.mk",
                      "a",
                      "b"
                    ],
                    "q"
                  ],
                  "a",
                  "b"
                ]
              ]
            ]
          }
        ]
      },
      "structure": {
        "fun": [
          [
            "_H",
            null
          ],
          [
            "q",
            null
          ],
          [
            "a",
            null
          ],
          [
            "b",
            null
          ]
        ],
        "body": [
          "And.intro",
          {
            "fun": [
              [
                "h",
                null
              ]
            ],
            "body": [
              "Foam.the_known_edge_already_reaches",
              "h"
            ]
          },
          {
            "fun": [
              [
                "hfresh",
                null
              ]
            ],
            "body": [
              "And.intro",
              {
                "fun": [
                  [
                    "_x",
                    null
                  ],
                  [
                    "_y",
                    null
                  ],
                  [
                    "p",
                    null
                  ]
                ],
                "body": [
                  "Foam.a_fresh_edge_rides_no_path",
                  "hfresh",
                  "p"
                ]
              },
              [
                "And.right",
                [
                  "Foam.only_surprise_extends_reach",
                  "q",
                  "a",
                  "b",
                  "hfresh"
                ]
              ]
            ]
          }
        ]
      }
    },
    {
      "term": "distinct_messages_need_distinct_marks",
      "gloss": "the converse side of coding, at its smallest: a lossless code gives distinct messages distinct marks, and a mark-space smaller than the message-space cannot supply them — two bits of message will not ride one bit of mark; on a two-valued wire some pair of the four collides. the constant cited was carved as the floor of contact width; read from this seat it is the zeroth coding bound, the counting argument the coding converses run at scale. this entry is the floor without the price — what the price is, on average, is the terminus's question.",
      "shape": "pigeonhole",
      "status": "sealed",
      "seal": "Foam.the_hallway_is_too_small"
    },
    {
      "term": "entropy_of_the_source",
      "gloss": "how much surprise, on average: the mind's own measure — maximal when the symbols are equiprobable, zero when the receiver can already reproduce everything. the price question the previous entry handed here is now posed in lean rather than prose: over the complete book at depth n — the equiprobable source, the one source already on the walls — any prefix-free marking (no mark a prefix of another; losslessness implied, since an equal mark is a trivial prefix) pays total mark-mass at least n per word. expectation enters the way the walls already read it: pool the marks and read the mass (Foam.pool, Foam.the_mass_is_a_reading) — no division, and no logarithm, because the log is performed by the book itself, doubling at each depth; the floor says the doubling source costs one mark per flip, on average, under every honest marking. the anchors ride along unpriced: the identity marking meets the floor, so at equiprobability it is exact and maximal; the singleton source is priced by the empty mark, zero. still vacancy-dark — a statement without a structure, the red of red-green, the engine already judging the hole well-posed; the carve that closes it is the zeroth converse (distinct_messages_need_distinct_marks) run at every depth at once — kraft's counting, a tree grind in pure nat. what survives the closing transits rather than dying: the book is the uniform source only — the biased source, its typical set, and the rates that price non-uniform surprise are a census the walls do not yet hold. the terminus, posed.",
      "shape": "measure",
      "status": "unsealed",
      "seal": null,
      "statement": {
        "all": [
          [
            "n",
            "Nat"
          ],
          [
            "f",
            {
              "all": [
                [
                  "_w",
                  [
                    "List",
                    "Bool"
                  ]
                ]
              ],
              "body": [
                "List",
                "Bool"
              ]
            }
          ],
          [
            "_hpf",
            {
              "all": [
                [
                  "w1",
                  [
                    "List",
                    "Bool"
                  ]
                ],
                [
                  "w2",
                  [
                    "List",
                    "Bool"
                  ]
                ],
                [
                  "_h1",
                  [
                    "List.Mem",
                    "w1",
                    [
                      "Foam.book",
                      "n"
                    ]
                  ]
                ],
                [
                  "_h2",
                  [
                    "List.Mem",
                    "w2",
                    [
                      "Foam.book",
                      "n"
                    ]
                  ]
                ],
                [
                  "_hne",
                  [
                    "Ne",
                    "w1",
                    "w2"
                  ]
                ]
              ],
              "body": [
                "Not",
                [
                  "Exists",
                  {
                    "fun": [
                      [
                        "t",
                        [
                          "List",
                          "Bool"
                        ]
                      ]
                    ],
                    "body": [
                      "Eq",
                      [
                        "List.append",
                        [
                          "f",
                          "w1"
                        ],
                        "t"
                      ],
                      [
                        "f",
                        "w2"
                      ]
                    ]
                  }
                ]
              ]
            }
          ]
        ],
        "body": [
          "Nat.le",
          [
            "Nat.mul",
            "n",
            [
              "List.length",
              [
                "Foam.book",
                "n"
              ]
            ]
          ],
          [
            "List.length",
            [
              "Foam.pool",
              [
                "List.map",
                "f",
                [
                  "Foam.book",
                  "n"
                ]
              ]
            ]
          ]
        ]
      }
    }
  ]
}
